golf_parity/__init__.py
golf_parity/__main__.py
golf_parity/arrays.py
golf_parity/fizzbuzz.p
golf_parity-0.0.2.dist-info/METADATA
golf_parity-0.0.2.dist-info/WHEEL
golf_parity-0.0.2.dist-info/entry_points.txt
golf_parity-0.0.2.dist-info/top_level.txt
golf_parity-0.0.2.dist-info/RECORD
