Metadata-Version: 2.1
Name: golf-parity
Version: 0.0.2
Summary: UNKNOWN
Home-page: https://github.com/cole-wilson/parity
Author: Cole Wilson
Author-email: cole@colewilson.xyz
License: none
Platform: UNKNOWN
Classifier: Programming Language :: Python :: 3
Requires-Python: >=3.6
Requires-Dist: typing
Requires-Dist: adicity
